<?xml version="1.0" encoding="UTF-8"?>
<factura id="comprobante" version="1.0.0">
<infoTributaria>
<razonSocial>ACERO COMERCIAL ECUATORIANO S.</razonSocial>
<nombreComercial>ACERO COMERCIAL</nombreComercial>
<ruc>1790008959001</ruc>
<estab>003</estab>
<ptoEmi>001</ptoEmi>
<secuencial>000131776</secuencial>
<dirMatriz>AV. DE LA PRENSA N45-14 Y EL TELEGRAFO 1</dirMatriz>
</infoTributaria>
<infoFactura>
<fechaEmision>23/12/2014</fechaEmision>
<dirEstablecimiento>GUALBERTO PEREZ E1-88 Y MALDONADO Y NAPO</dirEstablecimiento>
<contribuyenteEspecial>5368</contribuyenteEspecial>
<obligadoContabilidad>SI</obligadoContabilidad>
<tipoIdentificacionComprador>04</tipoIdentificacionComprador>
<guiaRemision>003-001-000131776</guiaRemision>
<razonSocialComprador>HIDALGO RUEDA EFRAIN VLADIMIR</razonSocialComprador>
<identificacionComprador>1712423266001</identificacionComprador>
<totalSinImpuestos>3.76</totalSinImpuestos>
<totalDescuento>0.00</totalDescuento>
<totalConImpuestos>
<totalImpuesto>
<codigo>2</codigo>
<codigoPorcentaje>2</codigoPorcentaje>
<descuentoAdicional>0.00</descuentoAdicional>
<baseImponible>3.76</baseImponible>
<valor>0.45</valor>
</totalImpuesto>
</totalConImpuestos>
<propina>0.00</propina>
<importeTotal>4.21</importeTotal>
<moneda>DOLAR</moneda>
</infoFactura>
<detalles>
<detalle>
<codigoPrincipal>95348</codigoPrincipal>
<descripcion>TEE GALV. CLASE 150 DE 1/2"</descripcion>
<cantidad>2.00</cantidad>
<precioUnitario>1.23</precioUnitario>
<descuento>0.00</descuento>
<precioTotalSinImpuesto>2.46</precioTotalSinImpuesto>
<detallesAdicionales>
<detAdicional nombre="MARCA" valor="CIFUNS"/>
<detAdicional nombre="UNIDAD" valor="UNIDAD"/>
</detallesAdicionales>
<impuestos>
<impuesto>
<codigo>2</codigo>
<codigoPorcentaje>2</codigoPorcentaje>
<tarifa>12.00</tarifa>
<baseImponible>2.46</baseImponible>
<valor>0.30</valor>
</impuesto>
</impuestos>
</detalle>
<detalle>
<codigoPrincipal>3166</codigoPrincipal>
<descripcion>NEPLO GALVANIZADO DE 1/2" x 4"</descripcion>
<cantidad>2.00</cantidad>
<precioUnitario>0.65</precioUnitario>
<descuento>0.00</descuento>
<precioTotalSinImpuesto>1.30</precioTotalSinImpuesto>
<detallesAdicionales>
<detAdicional nombre="MARCA" valor="NACION"/>
<detAdicional nombre="UNIDAD" valor="UNIDAD"/>
</detallesAdicionales>
<impuestos>
<impuesto>
<codigo>2</codigo>
<codigoPorcentaje>2</codigoPorcentaje>
<tarifa>12.00</tarifa>
<baseImponible>1.30</baseImponible>
<valor>0.16</valor>
</impuesto>
</impuestos>
</detalle>
</detalles>
<infoAdicional>
<campoAdicional nombre="Email">vladyhakiner@hotmail.com</campoAdicional>
<campoAdicional nombre="telefono-movil">2668306</campoAdicional>
<campoAdicional nombre="CodInternoSAP">039955</campoAdicional>
</infoAdicional>
</factura>
