<?xml version="1.0" encoding="UTF-8"?>
<factura id="comprobante" version="1.0.0">
<infoTributaria>
<razonSocial>ACERO COMERCIAL ECUATORIANO S.</razonSocial>
<nombreComercial>ACERO COMERCIAL</nombreComercial>
<ruc>1790008959001</ruc>
<estab>003</estab>
<ptoEmi>001</ptoEmi>
<secuencial>000114065</secuencial>
<dirMatriz>AV. DE LA PRENSA N45-14 Y EL TELEGRAFO 1</dirMatriz>
</infoTributaria>
<infoFactura>
<fechaEmision>22/01/2015</fechaEmision>
<dirEstablecimiento>GUALBERTO PEREZ E1-88 Y MALDONADO Y NAPO</dirEstablecimiento>
<contribuyenteEspecial>5368</contribuyenteEspecial>
<obligadoContabilidad>SI</obligadoContabilidad>
<tipoIdentificacionComprador>04</tipoIdentificacionComprador>
<guiaRemision>003-001-000114065</guiaRemision>
<razonSocialComprador>VIVAS AULESTIA WILMER ALIRO</razonSocialComprador>
<identificacionComprador>1710218957001</identificacionComprador>
<totalSinImpuestos>53.49</totalSinImpuestos>
<totalDescuento>5.04</totalDescuento>
<totalConImpuestos>
<totalImpuesto>
<codigo>2</codigo>
<codigoPorcentaje>2</codigoPorcentaje>
<descuentoAdicional>0.00</descuentoAdicional>
<baseImponible>53.49</baseImponible>
<valor>6.42</valor>
</totalImpuesto>
</totalConImpuestos>
<propina>0.00</propina>
<importeTotal>59.91</importeTotal>
<moneda>DOLAR</moneda>
</infoFactura>
<detalles>
<detalle>
<codigoPrincipal>3664</codigoPrincipal>
<descripcion>REDUCCION GALV. CLASE 150 DE 1-1/2" x 3/4"</descripcion>
<cantidad>5.00</cantidad>
<precioUnitario>3.49</precioUnitario>
<descuento>1.75</descuento>
<precioTotalSinImpuesto>15.70</precioTotalSinImpuesto>
<detallesAdicionales>
<detAdicional nombre="MARCA" valor="HITACH"/>
<detAdicional nombre="UNIDAD" valor="UNIDAD"/>
</detallesAdicionales>
<impuestos>
<impuesto>
<codigo>2</codigo>
<codigoPorcentaje>2</codigoPorcentaje>
<tarifa>12.00</tarifa>
<baseImponible>15.70</baseImponible>
<valor>1.88</valor>
</impuesto>
</impuestos>
</detalle>
<detalle>
<codigoPrincipal>4573</codigoPrincipal>
<descripcion>TEE GALV. CLASE 150 DE 1-1/2"</descripcion>
<cantidad>2.00</cantidad>
<precioUnitario>6.07</precioUnitario>
<descuento>0.97</descuento>
<precioTotalSinImpuesto>11.17</precioTotalSinImpuesto>
<detallesAdicionales>
<detAdicional nombre="MARCA" valor="CIFUNS"/>
<detAdicional nombre="UNIDAD" valor="UNIDAD"/>
</detallesAdicionales>
<impuestos>
<impuesto>
<codigo>2</codigo>
<codigoPorcentaje>2</codigoPorcentaje>
<tarifa>12.00</tarifa>
<baseImponible>11.17</baseImponible>
<valor>1.34</valor>
</impuesto>
</impuestos>
</detalle>
<detalle>
<codigoPrincipal>2063</codigoPrincipal>
<descripcion>CODO GALV. CLASE 150 90 GRAD  DE 1-1/2"</descripcion>
<cantidad>3.00</cantidad>
<precioUnitario>4.57</precioUnitario>
<descuento>1.10</descuento>
<precioTotalSinImpuesto>12.61</precioTotalSinImpuesto>
<detallesAdicionales>
<detAdicional nombre="MARCA" valor="CIFUNS"/>
<detAdicional nombre="UNIDAD" valor="UNIDAD"/>
</detallesAdicionales>
<impuestos>
<impuesto>
<codigo>2</codigo>
<codigoPorcentaje>2</codigoPorcentaje>
<tarifa>12.00</tarifa>
<baseImponible>12.61</baseImponible>
<valor>1.51</valor>
</impuesto>
</impuestos>
</detalle>
<detalle>
<codigoPrincipal>3232</codigoPrincipal>
<descripcion>NEPLO GALVANIZADO DE 1-1/2" CORRIDO</descripcion>
<cantidad>3.00</cantidad>
<precioUnitario>1.21</precioUnitario>
<descuento>0.29</descuento>
<precioTotalSinImpuesto>3.34</precioTotalSinImpuesto>
<detallesAdicionales>
<detAdicional nombre="MARCA" valor="NACION"/>
<detAdicional nombre="UNIDAD" valor="UNIDAD"/>
</detallesAdicionales>
<impuestos>
<impuesto>
<codigo>2</codigo>
<codigoPorcentaje>2</codigoPorcentaje>
<tarifa>12.00</tarifa>
<baseImponible>3.34</baseImponible>
<valor>0.40</valor>
</impuesto>
</impuestos>
</detalle>
<detalle>
<codigoPrincipal>97467</codigoPrincipal>
<descripcion>TEFLON EN ROLLO 0.07 x 12 mm. x 10 m.</descripcion>
<cantidad>20.00</cantidad>
<precioUnitario>0.58</precioUnitario>
<descuento>0.93</descuento>
<precioTotalSinImpuesto>10.67</precioTotalSinImpuesto>
<detallesAdicionales>
<detAdicional nombre="MARCA" valor="PLASTI"/>
<detAdicional nombre="UNIDAD" valor="UNIDAD"/>
</detallesAdicionales>
<impuestos>
<impuesto>
<codigo>2</codigo>
<codigoPorcentaje>2</codigoPorcentaje>
<tarifa>12.00</tarifa>
<baseImponible>10.67</baseImponible>
<valor>1.28</valor>
</impuesto>
</impuestos>
</detalle>
</detalles>
<infoAdicional>
<campoAdicional nombre="Email">transwvivas@hotmail.com</campoAdicional>
<campoAdicional nombre="telefono-movil">2675793</campoAdicional>
<campoAdicional nombre="CodInternoSAP">064350</campoAdicional>
<campoAdicional nombre="Observaciones">CRUZA N/C: 4386 SALDO EN EFECTIVO</campoAdicional>
</infoAdicional>
</factura>
