<?xml version="1.0" encoding="UTF-8"?>
<guiaRemision id="comprobante" version="1.0.0">
<infoTributaria>
<razonSocial>ACERO COMERCIAL ECUATORIANO S.A.</razonSocial>
<nombreComercial>ACERO COMERCIAL</nombreComercial>
<ruc>1790008959001</ruc>
<estab>009</estab>
<ptoEmi>001</ptoEmi>
<secuencial>000025631</secuencial>
<dirMatriz>AV.DE LA PRENSA N45-14 Y TELEGRAFO 1</dirMatriz>
</infoTributaria>
<infoGuiaRemision>
<dirEstablecimiento>KM 1.7 AV. JUAN TANCA MARENGO</dirEstablecimiento>
<dirPartida>ACERO COMERCIAL J T MARENGO KM 1.7</dirPartida>
<razonSocialTransportista>HERNAEZ ZAMBRANO LUIS</razonSocialTransportista>
<tipoIdentificacionTransportista>04</tipoIdentificacionTransportista>
<rucTransportista>1308052545001</rucTransportista>
<obligadoContabilidad>SI</obligadoContabilidad>
<contribuyenteEspecial>5368</contribuyenteEspecial>
<fechaIniTransporte>05/01/2015</fechaIniTransporte>
<fechaFinTransporte>06/01/2015</fechaFinTransporte>
<placa>MBA3623</placa>
</infoGuiaRemision>
<destinatarios>
<destinatario>
<identificacionDestinatario>1308052545001</identificacionDestinatario>
<razonSocialDestinatario>HERNAEZ ZAMBRANO LUIS</razonSocialDestinatario>
<dirDestinatario>RETIRAN</dirDestinatario>
<motivoTraslado>VENTA</motivoTraslado>
<fechaEmisionDocSustento>05/01/2015</fechaEmisionDocSustento>
<detalles>
<detalle>
<codigoInterno>94203</codigoInterno>
<descripcion>MOTOR ELEC SUMERG DE 4" DE 1 HP 115V/1F/60C (2545189003S)</descripcion>
<cantidad>1.00</cantidad>
<detallesAdicionales>
<detAdicional nombre="MARCA" valor="FRANKL"/>
<detAdicional nombre="UNIDAD" valor="UNIDAD"/>
</detallesAdicionales>
</detalle>
<detalle>
<codigoInterno>94204</codigoInterno>
<descripcion>CAJA DE ARRANQUE BX 115V/1F/60C (2842088500)</descripcion>
<cantidad>1.00</cantidad>
<detallesAdicionales>
<detAdicional nombre="MARCA" valor="FRANKL"/>
<detAdicional nombre="UNIDAD" valor="UNIDAD"/>
</detallesAdicionales>
</detalle>
</detalles>
</destinatario>
</destinatarios>
<infoAdicional>
<campoAdicional nombre="Email">luis_h_ernaez@hotmail.com</campoAdicional>
<campoAdicional nombre="telefono-movil">097276494</campoAdicional>
<campoAdicional nombre="CodInternoSAP">014503</campoAdicional>
</infoAdicional>
</guiaRemision>
