<?xml version="1.0" encoding="UTF-8"?>
<factura id="comprobante" version="1.0.0">
<infoTributaria>
<razonSocial>ACERO COMERCIAL ECUATORIANO S.A.</razonSocial>
<nombreComercial>ACERO COMERCIAL</nombreComercial>
<ruc>1790008959001</ruc>
<estab>004</estab>
<ptoEmi>001</ptoEmi>
<secuencial>000268951</secuencial>
<dirMatriz>AV.DE LA PRENSA N45-14 Y TELEGRAFO 1</dirMatriz>
</infoTributaria>
<infoFactura>
<fechaEmision>24/01/2015</fechaEmision>
<dirEstablecimiento>AV. LA PRENSA - MATRIZ QUITO</dirEstablecimiento>
<contribuyenteEspecial>5368</contribuyenteEspecial>
<obligadoContabilidad>SI</obligadoContabilidad>
<tipoIdentificacionComprador>04</tipoIdentificacionComprador>
<guiaRemision>004-001-000268951</guiaRemision>
<razonSocialComprador>AREVALO SAQUICELA LUIS MARCELO</razonSocialComprador>
<identificacionComprador>1705244190001</identificacionComprador>
<totalSinImpuestos>174.67</totalSinImpuestos>
<totalDescuento>30.83</totalDescuento>
<totalConImpuestos>
<totalImpuesto>
<codigo>2</codigo>
<codigoPorcentaje>2</codigoPorcentaje>
<descuentoAdicional>0.00</descuentoAdicional>
<baseImponible>174.67</baseImponible>
<valor>20.96</valor>
</totalImpuesto>
</totalConImpuestos>
<propina>0.00</propina>
<importeTotal>195.63</importeTotal>
<moneda>DOLAR</moneda>
</infoFactura>
<detalles>
<detalle>
<codigoPrincipal>103043</codigoPrincipal>
<descripcion>BALDOSA DE PISO 30 X 30 MONOQUEMA SPINETTO CREMA SEGUNDA</descripcion>
<cantidad>30.00</cantidad>
<precioUnitario>6.85</precioUnitario>
<descuento>30.83</descuento>
<precioTotalSinImpuesto>174.67</precioTotalSinImpuesto>
<detallesAdicionales>
<detAdicional nombre="MARCA" valor="RIALTO"/>
<detAdicional nombre="UNIDAD" valor="M2"/>
</detallesAdicionales>
<impuestos>
<impuesto>
<codigo>2</codigo>
<codigoPorcentaje>2</codigoPorcentaje>
<tarifa>12.00</tarifa>
<baseImponible>174.67</baseImponible>
<valor>20.96</valor>
</impuesto>
</impuestos>
</detalle>
</detalles>
<infoAdicional>
<campoAdicional nombre="Email">marceloarevalo4@hotmail.com</campoAdicional>
<campoAdicional nombre="telefono-movil">2530313</campoAdicional>
<campoAdicional nombre="CodInternoSAP">046251</campoAdicional>
<campoAdicional nombre="Observaciones">PIDE SRA. VENUS</campoAdicional>
</infoAdicional>
</factura>
