<?xml version="1.0" encoding="UTF-8"?>
<factura id="comprobante" version="1.0.0">
<infoTributaria>
<razonSocial>ACERO COMERCIAL ECUATORIANO S.A.</razonSocial>
<nombreComercial>ACERO COMERCIAL</nombreComercial>
<ruc>1790008959001</ruc>
<estab>004</estab>
<ptoEmi>001</ptoEmi>
<secuencial>000175858</secuencial>
<dirMatriz>AV.DE LA PRENSA N45-14 Y TELEGRAFO 1</dirMatriz>
</infoTributaria>
<infoFactura>
<fechaEmision>15/12/2014</fechaEmision>
<dirEstablecimiento>DAVID LEDESMA N69-31 Y MIGUEL MORENO</dirEstablecimiento>
<contribuyenteEspecial>5368</contribuyenteEspecial>
<obligadoContabilidad>SI</obligadoContabilidad>
<tipoIdentificacionComprador>04</tipoIdentificacionComprador>
<guiaRemision>004-001-000175858</guiaRemision>
<razonSocialComprador>FERRITUVALCO CIA. LTDA.</razonSocialComprador>
<identificacionComprador>1792073898001</identificacionComprador>
<totalSinImpuestos>190.40</totalSinImpuestos>
<totalDescuento>19.04</totalDescuento>
<totalConImpuestos>
<totalImpuesto>
<codigo>2</codigo>
<codigoPorcentaje>2</codigoPorcentaje>
<descuentoAdicional>0.00</descuentoAdicional>
<baseImponible>171.36</baseImponible>
<valor>20.56</valor>
</totalImpuesto>
</totalConImpuestos>
<propina>0.00</propina>
<importeTotal>191.92</importeTotal>
<moneda>DOLAR</moneda>
</infoFactura>
<detalles>
<detalle>
<codigoPrincipal>44300</codigoPrincipal>
<descripcion>COQUILLA LANA DE VIDRIO C-ALUMINIO 1" x 1" x 0.90 m.</descripcion>
<cantidad>34.00</cantidad>
<precioUnitario>5.60</precioUnitario>
<descuento>19.04</descuento>
<precioTotalSinImpuesto>171.36</precioTotalSinImpuesto>
<detallesAdicionales>
<detAdicional nombre="ANDIFIBRAS" valor="ANDIFI"/>
<detAdicional nombre="UNIDAD" valor="UNIDAD"/>
</detallesAdicionales>
<impuestos>
<impuesto>
<codigo>2</codigo>
<codigoPorcentaje>2</codigoPorcentaje>
<tarifa>12.00</tarifa>
<baseImponible>171.36</baseImponible>
<valor>20.56</valor>
</impuesto>
</impuestos>
</detalle>
</detalles>
<infoAdicional>
<campoAdicional nombre="Email"></campoAdicional>
</infoAdicional>
</factura>
