<?xml version="1.0" encoding="UTF-8"?>
<factura id="comprobante" version="1.0.0">
<infoTributaria>
<razonSocial>ACERO COMERCIAL ECUATORIANO S.A.</razonSocial>
<nombreComercial>ACERO COMERCIAL</nombreComercial>
<ruc>1790008959001</ruc>
<estab>004</estab>
<ptoEmi>001</ptoEmi>
<secuencial>000176390</secuencial>
<dirMatriz>AV.DE LA PRENSA N45-14 Y TELEGRAFO 1</dirMatriz>
</infoTributaria>
<infoFactura>
<fechaEmision>29/12/2014</fechaEmision>
<dirEstablecimiento>AV. LA PRENSA - MATRIZ QUITO</dirEstablecimiento>
<contribuyenteEspecial>5368</contribuyenteEspecial>
<obligadoContabilidad>SI</obligadoContabilidad>
<tipoIdentificacionComprador>05</tipoIdentificacionComprador>
<guiaRemision>004-001-000176390</guiaRemision>
<razonSocialComprador>VALENCIA SALA GLADYS IVONNE</razonSocialComprador>
<identificacionComprador>1702953280</identificacionComprador>
<totalSinImpuestos>357.50</totalSinImpuestos>
<totalDescuento>0.00</totalDescuento>
<totalConImpuestos>
<totalImpuesto>
<codigo>2</codigo>
<codigoPorcentaje>2</codigoPorcentaje>
<descuentoAdicional>0.00</descuentoAdicional>
<baseImponible>357.50</baseImponible>
<valor>42.90</valor>
</totalImpuesto>
</totalConImpuestos>
<propina>0.00</propina>
<importeTotal>400.40</importeTotal>
<moneda>DOLAR</moneda>
</infoFactura>
<detalles>
<detalle>
<codigoPrincipal>101370</codigoPrincipal>
<descripcion>CALENTADOR DE AGUA 220 V AISLADO 40 GL. 220V. C/TERMOMETRO</descripcion>
<cantidad>1.00</cantidad>
<precioUnitario>357.50</precioUnitario>
<descuento>0.00</descuento>
<precioTotalSinImpuesto>357.50</precioTotalSinImpuesto>
<detallesAdicionales>
<detAdicional nombre="MARCA" valor="NACION"/>
<detAdicional nombre="UNIDAD" valor="UNIDAD"/>
</detallesAdicionales>
<impuestos>
<impuesto>
<codigo>2</codigo>
<codigoPorcentaje>2</codigoPorcentaje>
<tarifa>12.00</tarifa>
<baseImponible>357.50</baseImponible>
<valor>42.90</valor>
</impuesto>
</impuestos>
</detalle>
</detalles>
<infoAdicional>
<campoAdicional nombre="Email">valenciasala@yahoo.com</campoAdicional>
<campoAdicional nombre="telefono-movil">2896228</campoAdicional>
<campoAdicional nombre="CodInternoSAP">063896</campoAdicional>
</infoAdicional>
</factura>
