<?xml version="1.0" encoding="UTF-8"?>
<guiaRemision id="comprobante" version="1.0.0">
<infoTributaria>
<razonSocial>ACERO COMERCIAL ECUATORIANO S.A.</razonSocial>
<nombreComercial>ACERO COMERCIAL</nombreComercial>
<ruc>1790008959001</ruc>
<estab>004</estab>
<ptoEmi>001</ptoEmi>
<secuencial>000041329</secuencial>
<dirMatriz>AV.DE LA PRENSA N45-14 Y TELEGRAFO 1</dirMatriz>
</infoTributaria>
<infoGuiaRemision>
<dirEstablecimiento>AV.DE LA PRENSA N45-14 Y TELEGRAFO 1</dirEstablecimiento>
<dirPartida>AV DE LA PRENSA</dirPartida>
<razonSocialTransportista>SERGIO QUINCHE</razonSocialTransportista>
<tipoIdentificacionTransportista>04</tipoIdentificacionTransportista>
<rucTransportista>1790008959001</rucTransportista>
<obligadoContabilidad>SI</obligadoContabilidad>
<contribuyenteEspecial>5368</contribuyenteEspecial>
<fechaIniTransporte>05/01/2015</fechaIniTransporte>
<fechaFinTransporte>05/01/2015</fechaFinTransporte>
<placa>D51D54</placa>
</infoGuiaRemision>
<destinatarios>
<destinatario>
<identificacionDestinatario>1790008959001</identificacionDestinatario>
<razonSocialDestinatario>ACERO COMERCIAL ECUATORIANO S.A.</razonSocialDestinatario>
<dirDestinatario>ACERO SUR GUALBERTO PEREZ</dirDestinatario>
<motivoTraslado>TRANSFERENCIAS ENTRE LOCALIDADES</motivoTraslado>
<fechaEmisionDocSustento>05/01/2015</fechaEmisionDocSustento>
<detalles>
<detalle>
<codigoInterno>5504</codigoInterno>
<descripcion>TUBO GALV. S-UNION ISO II TIPO "T" DE 2-1/2" x 6 m. ESPESOR 3.2 mm.</descripcion>
<cantidad>6.00</cantidad>
<detallesAdicionales>
<detAdicional nombre="MARCA" valor="TUGALT"/>
<detAdicional nombre="UNIDAD" valor="UNIDAD"/>
</detallesAdicionales>
</detalle>
<detalle>
<codigoInterno>94827</codigoInterno>
<descripcion>TERMOMETRO IR-100 MICRO RAY INFRAROJO (36153)</descripcion>
<cantidad>2.00</cantidad>
<detallesAdicionales>
<detAdicional nombre="MARCA" valor="RIDGID"/>
<detAdicional nombre="UNIDAD" valor="UNIDAD"/>
</detallesAdicionales>
</detalle>
<detalle>
<codigoInterno>98581</codigoInterno>
<descripcion>BOMBA CENTRIF MULTIETAPA C-MOTOR CM3-6 ASGE  1" X 1" 2HP 115/230V/60/1F AVBE (96935597)</descripcion>
<cantidad>1.00</cantidad>
<detallesAdicionales>
<detAdicional nombre="MARCA" valor="GRUNDF"/>
<detAdicional nombre="UNIDAD" valor="UNIDAD"/>
</detallesAdicionales>
</detalle>
<detalle>
<codigoInterno>150609</codigoInterno>
<descripcion>ANCLAJE EPOXICO 8486SD DE 12oz AC100</descripcion>
<cantidad>8.00</cantidad>
<detallesAdicionales>
<detAdicional nombre="MARCA" valor="POWERS"/>
<detAdicional nombre="UNIDAD" valor="UNIDAD"/>
</detallesAdicionales>
</detalle>
<detalle>
<codigoInterno>15666</codigoInterno>
<descripcion>DADOS PARA TERRAJA MANUAL P/ 12-R DE 3/4" NPT (37830)</descripcion>
<cantidad>3.00</cantidad>
<detallesAdicionales>
<detAdicional nombre="MARCA" valor="RIDGID"/>
<detAdicional nombre="UNIDAD" valor="UNIDAD"/>
</detallesAdicionales>
</detalle>
<detalle>
<codigoInterno>1666</codigoInterno>
<descripcion>BUSHING GALV. CLASE 150 DE 2-1/2" x 1"</descripcion>
<cantidad>10.00</cantidad>
<detallesAdicionales>
<detAdicional nombre="MARCA" valor="HITACH"/>
<detAdicional nombre="UNIDAD" valor="UNIDAD"/>
</detallesAdicionales>
</detalle>
<detalle>
<codigoInterno>3292</codigoInterno>
<descripcion>NEPLO GALVANIZADO DE 3" x 4"</descripcion>
<cantidad>3.00</cantidad>
<detallesAdicionales>
<detAdicional nombre="MARCA" valor="NACION"/>
<detAdicional nombre="UNIDAD" valor="UNIDAD"/>
</detallesAdicionales>
</detalle>
<detalle>
<codigoInterno>3296</codigoInterno>
<descripcion>NEPLO GALVANIZADO DE 3" x 6"</descripcion>
<cantidad>4.00</cantidad>
<detallesAdicionales>
<detAdicional nombre="MARCA" valor="NACION"/>
<detAdicional nombre="UNIDAD" valor="UNIDAD"/>
</detallesAdicionales>
</detalle>
<detalle>
<codigoInterno>3350</codigoInterno>
<descripcion>NEPLO NEGRO DE 1/2" CORRIDO</descripcion>
<cantidad>15.00</cantidad>
<detallesAdicionales>
<detAdicional nombre="MARCA" valor="NACION"/>
<detAdicional nombre="UNIDAD" valor="UNIDAD"/>
</detallesAdicionales>
</detalle>
<detalle>
<codigoInterno>5826</codigoInterno>
<descripcion>TUBO PVC ROSCABLE x 6 MTS. DE 1/2" (420 PSI)</descripcion>
<cantidad>30.00</cantidad>
<detallesAdicionales>
<detAdicional nombre="MARCA" valor="PLASTI"/>
<detAdicional nombre="UNIDAD" valor="UNIDAD"/>
</detallesAdicionales>
</detalle>
<detalle>
<codigoInterno>92019</codigoInterno>
<descripcion>CODO NEGRO CLASE 150 DE 1/2" x 90ø</descripcion>
<cantidad>30.00</cantidad>
<detallesAdicionales>
<detAdicional nombre="MARCA" valor="CIFUNS"/>
<detAdicional nombre="UNIDAD" valor="UNIDAD"/>
</detallesAdicionales>
</detalle>
<detalle>
<codigoInterno>96914</codigoInterno>
<descripcion>CABLE DE CORRIENTE 22-64-3050  P/MOTOR 4262-1</descripcion>
<cantidad>1.00</cantidad>
<detallesAdicionales>
<detAdicional nombre="MARCA" valor="MILWAU"/>
<detAdicional nombre="UNIDAD" valor="UNIDAD"/>
</detallesAdicionales>
</detalle>
</detalles>
</destinatario>
</destinatarios>
<infoAdicional>
<campoAdicional nombre="Email">facturacionelectrónica@acerocomercial.com</campoAdicional>
<campoAdicional nombre="telefono-movil">022454333</campoAdicional>
<campoAdicional nombre="CodInternoSAP">000003</campoAdicional>
</infoAdicional>
</guiaRemision>
