<?xml version="1.0" encoding="UTF-8"?>
<notaCredito id="comprobante" version="1.0.0">
<infoTributaria>
<razonSocial>ACERO COMERCIAL ECUATORIANO S.A.</razonSocial>
<nombreComercial>ACERO COMERCIAL</nombreComercial>
<ruc>1790008959001</ruc>
<estab>004</estab>
<ptoEmi>001</ptoEmi>
<secuencial>000025213</secuencial>
<dirMatriz>AV.DE LA PRENSA N45-14 Y TELEGRAFO 1</dirMatriz>
</infoTributaria>
<infoNotaCredito>
<fechaEmision>19/01/2015</fechaEmision>
<dirEstablecimiento>AV. LA PRENSA - MATRIZ QUITO</dirEstablecimiento>
<tipoIdentificacionComprador>04</tipoIdentificacionComprador>
<razonSocialComprador>MEZA ESCALANTE ALVARO MIGUEL</razonSocialComprador>
<identificacionComprador>1712210275001</identificacionComprador>
<contribuyenteEspecial>5368</contribuyenteEspecial>
<obligadoContabilidad>SI</obligadoContabilidad>
<codDocModificado>01</codDocModificado>
<numDocModificado>004-001-000174900</numDocModificado>
<fechaEmisionDocSustento>27/11/2014</fechaEmisionDocSustento>
<totalSinImpuestos>508.21</totalSinImpuestos>
<valorModificacion>569.20</valorModificacion>
<moneda>DOLAR</moneda>
<totalConImpuestos>
<totalImpuesto>
<codigo>2</codigo>
<codigoPorcentaje>2</codigoPorcentaje>
<baseImponible>508.21</baseImponible>
<valor>60.99</valor>
</totalImpuesto>
</totalConImpuestos>
<motivo>DEV 266559 ALVARO MEZA PASO A DQ SHERRER</motivo>
</infoNotaCredito>
<detalles>
<detalle>
<codigoInterno>99601</codigoInterno>
<descripcion>SIERRA CIRCULAR A BATERIA 2630-22  LITIO-ION 18V. 3500RPM</descripcion>
<cantidad>1.00</cantidad>
<precioUnitario>597.90</precioUnitario>
<descuento>89.69</descuento>
<precioTotalSinImpuesto>508.21</precioTotalSinImpuesto>
<detallesAdicionales>
<detAdicional nombre="MARCA" valor="MILWAU"/>
<detAdicional nombre="UNIDAD" valor="UNIDAD"/>
</detallesAdicionales>
<impuestos>
<impuesto>
<codigo>2</codigo>
<codigoPorcentaje>2</codigoPorcentaje>
<tarifa>12.00</tarifa>
<baseImponible>508.21</baseImponible>
<valor>60.99</valor>
</impuesto>
</impuestos>
</detalle>
</detalles>
<infoAdicional>
<campoAdicional nombre="Email">alvaromeza9@hotmail.com</campoAdicional>
<campoAdicional nombre="telefono-movil">032518309</campoAdicional>
<campoAdicional nombre="CodInternoSAP">50223</campoAdicional>
</infoAdicional>
</notaCredito>
