<?xml version="1.0" encoding="UTF-8"?>
<guiaRemision id="comprobante" version="1.0.0">
<infoTributaria>
<razonSocial>ACERO COMERCIAL ECUATORIANO S.A.</razonSocial>
<nombreComercial>ACERO COMERCIAL</nombreComercial>
<ruc>1790008959001</ruc>
<estab>009</estab>
<ptoEmi>001</ptoEmi>
<secuencial>000025699</secuencial>
<dirMatriz>AV.DE LA PRENSA N45-14 Y TELEGRAFO 1</dirMatriz>
</infoTributaria>
<infoGuiaRemision>
<dirEstablecimiento>KM 1.7 AV. JUAN TANCA MARENGO</dirEstablecimiento>
<dirPartida>ACERO COMERCIAL J T MARENGO KM 1.7</dirPartida>
<razonSocialTransportista>T GUTIERREZ</razonSocialTransportista>
<tipoIdentificacionTransportista>04</tipoIdentificacionTransportista>
<rucTransportista>1790008959001</rucTransportista>
<obligadoContabilidad>SI</obligadoContabilidad>
<contribuyenteEspecial>5368</contribuyenteEspecial>
<fechaIniTransporte>09/01/2015</fechaIniTransporte>
<fechaFinTransporte>10/01/2015</fechaFinTransporte>
<placa>GSL5009</placa>
</infoGuiaRemision>
<destinatarios>
<destinatario>
<identificacionDestinatario>1310493778001</identificacionDestinatario>
<razonSocialDestinatario>OCANA LOPEZ JACQUELINE ELIZABETH</razonSocialDestinatario>
<dirDestinatario>MAQUINARIAS HENRIQUEZ KM 6,5 VIA A DAULE</dirDestinatario>
<motivoTraslado>VENTA</motivoTraslado>
<fechaEmisionDocSustento>09/01/2015</fechaEmisionDocSustento>
<detalles>
<detalle>
<codigoInterno>20662</codigoInterno>
<descripcion>MOTOR ELEC SUMERG DE 4" (2243019204S) SJF-2021 DE 2HP 230-1-60</descripcion>
<cantidad>1.00</cantidad>
<detallesAdicionales>
<detAdicional nombre="MARCA" valor="FRANKL"/>
<detAdicional nombre="UNIDAD" valor="UNIDAD"/>
</detallesAdicionales>
</detalle>
</detalles>
</destinatario>
</destinatarios>
<infoAdicional>
<campoAdicional nombre="Email">josvem2@hotmail.com</campoAdicional>
<campoAdicional nombre="telefono-movil">0992425067</campoAdicional>
<campoAdicional nombre="CodInternoSAP">016710</campoAdicional>
</infoAdicional>
</guiaRemision>
