<?xml version="1.0" encoding="UTF-8"?>
<factura id="comprobante" version="1.0.0">
<infoTributaria>
<razonSocial>ACERO COMERCIAL ECUATORIANO S.A.</razonSocial>
<nombreComercial>ACERO COMERCIAL</nombreComercial>
<ruc>1790008959001</ruc>
<estab>004</estab>
<ptoEmi>001</ptoEmi>
<secuencial>000268733</secuencial>
<dirMatriz>AV.DE LA PRENSA N45-14 Y TELEGRAFO 1</dirMatriz>
</infoTributaria>
<infoFactura>
<fechaEmision>20/01/2015</fechaEmision>
<dirEstablecimiento>AV. LA PRENSA - MATRIZ QUITO</dirEstablecimiento>
<contribuyenteEspecial>5368</contribuyenteEspecial>
<obligadoContabilidad>SI</obligadoContabilidad>
<tipoIdentificacionComprador>05</tipoIdentificacionComprador>
<guiaRemision>004-001-000268733</guiaRemision>
<razonSocialComprador>PACHECO GUERRA SILVIA JANNETH</razonSocialComprador>
<identificacionComprador>1708926330</identificacionComprador>
<totalSinImpuestos>3.31</totalSinImpuestos>
<totalDescuento>0.21</totalDescuento>
<totalConImpuestos>
<totalImpuesto>
<codigo>2</codigo>
<codigoPorcentaje>2</codigoPorcentaje>
<descuentoAdicional>0.00</descuentoAdicional>
<baseImponible>3.31</baseImponible>
<valor>0.40</valor>
</totalImpuesto>
</totalConImpuestos>
<propina>0.00</propina>
<importeTotal>3.71</importeTotal>
<moneda>DOLAR</moneda>
</infoFactura>
<detalles>
<detalle>
<codigoPrincipal>10</codigoPrincipal>
<descripcion>ALAMBRE GALVANIZADO N.12</descripcion>
<cantidad>1.00</cantidad>
<precioUnitario>2.26</precioUnitario>
<descuento>0.09</descuento>
<precioTotalSinImpuesto>2.17</precioTotalSinImpuesto>
<detallesAdicionales>
<detAdicional nombre="MARCA" valor="IDEAL"/>
<detAdicional nombre="UNIDAD" valor="KILO"/>
</detallesAdicionales>
<impuestos>
<impuesto>
<codigo>2</codigo>
<codigoPorcentaje>2</codigoPorcentaje>
<tarifa>12.00</tarifa>
<baseImponible>2.17</baseImponible>
<valor>0.26</valor>
</impuesto>
</impuestos>
</detalle>
<detalle>
<codigoPrincipal>50356</codigoPrincipal>
<descripcion>TAPON POLIPROPILENO HEMBRA DE 1/2" HEMBRA (AGUA CALIENTE)</descripcion>
<cantidad>1.00</cantidad>
<precioUnitario>0.34</precioUnitario>
<descuento>0.03</descuento>
<precioTotalSinImpuesto>0.31</precioTotalSinImpuesto>
<detallesAdicionales>
<detAdicional nombre="MARCA" valor="PLASTI"/>
<detAdicional nombre="UNIDAD" valor="UNIDAD"/>
</detallesAdicionales>
<impuestos>
<impuesto>
<codigo>2</codigo>
<codigoPorcentaje>2</codigoPorcentaje>
<tarifa>12.00</tarifa>
<baseImponible>0.31</baseImponible>
<valor>0.04</valor>
</impuesto>
</impuestos>
</detalle>
<detalle>
<codigoPrincipal>50368</codigoPrincipal>
<descripcion>TAPON POLIPROPILENO MACHO DE 1/2" MACHO (AGUA CALIENTE)</descripcion>
<cantidad>1.00</cantidad>
<precioUnitario>0.34</precioUnitario>
<descuento>0.03</descuento>
<precioTotalSinImpuesto>0.31</precioTotalSinImpuesto>
<detallesAdicionales>
<detAdicional nombre="MARCA" valor="PLASTI"/>
<detAdicional nombre="UNIDAD" valor="UNIDAD"/>
</detallesAdicionales>
<impuestos>
<impuesto>
<codigo>2</codigo>
<codigoPorcentaje>2</codigoPorcentaje>
<tarifa>12.00</tarifa>
<baseImponible>0.31</baseImponible>
<valor>0.04</valor>
</impuesto>
</impuestos>
</detalle>
<detalle>
<codigoPrincipal>97467</codigoPrincipal>
<descripcion>TEFLON EN ROLLO 0.07 x 12 mm. x 10 m.</descripcion>
<cantidad>1.00</cantidad>
<precioUnitario>0.58</precioUnitario>
<descuento>0.06</descuento>
<precioTotalSinImpuesto>0.52</precioTotalSinImpuesto>
<detallesAdicionales>
<detAdicional nombre="MARCA" valor="PLASTI"/>
<detAdicional nombre="UNIDAD" valor="UNIDAD"/>
</detallesAdicionales>
<impuestos>
<impuesto>
<codigo>2</codigo>
<codigoPorcentaje>2</codigoPorcentaje>
<tarifa>12.00</tarifa>
<baseImponible>0.52</baseImponible>
<valor>0.06</valor>
</impuesto>
</impuestos>
</detalle>
</detalles>
<infoAdicional>
<campoAdicional nombre="Email">jpacheco@vicunha.com</campoAdicional>
<campoAdicional nombre="telefono-movil">2422031</campoAdicional>
<campoAdicional nombre="CodInternoSAP">056092</campoAdicional>
</infoAdicional>
</factura>
